<?xml version="1.0"?>
<GainCapitalConfiguration xmlns:xsi="http://www.w3.org/2001/XMLSchema-instance" xmlns:xsd="http://www.w3.org/2001/XMLSchema">
  <Pricing>
    <Host>FIXQUOTE-UAT.LOGINANDTRADE.COM</Host>
    <Port>5004</Port>
    <TargetCompId>GC.FIXENGINE.UAT.PRICESERVER</TargetCompId>
    <SenderCompId>GC.FIXCLIENT.LANDFX</SenderCompId>
    <Username>XX366716</Username>
    <Password>abcd1234</Password>
  </Pricing>
  <Trading>
    <Host>FIXTRADE-UAT.LOGINANDTRADE.COM</Host>
    <Port>5001</Port>
    <TargetCompId>GC.FIXENGINE.UAT.ORDERSERVER</TargetCompId>
    <SenderCompId>GC.FIXCLIENT.LANDFX</SenderCompId>
    <Username>XX367357</Username>
    <Password>abcd1234</Password>
    <TradingAccountNumber>401288750</TradingAccountNumber>
  </Trading>
  <Heartbeat>30</Heartbeat>
</GainCapitalConfiguration>